setup.py
toredis/__init__.py
toredis/_compat.py
toredis/client.py
toredis/commands.py
toredis_fork.egg-info/PKG-INFO
toredis_fork.egg-info/SOURCES.txt
toredis_fork.egg-info/dependency_links.txt
toredis_fork.egg-info/requires.txt
toredis_fork.egg-info/top_level.txt