Metadata-Version: 1.0
Name: toredis-fork
Version: 0.1.2
Summary: Really simple async Redis client for Tornado
Home-page: http://github.com/mrjoes/toredis/
Author: Josh Marshall
Author-email: catchjosh@gmail.com
License: http://www.apache.org/licenses/LICENSE-2.0
Platform: UNKNOWN
